etcd3wrapper/__init__.py
etcd3wrapper/auth.py
etcd3wrapper/helpers.py
etcd3wrapper/kv.py
etcd3wrapper/rpc.py
etcd3wrapper/_autogen/__init__.py
etcd3wrapper/_autogen/etcd/__init__.py
etcd3wrapper/_autogen/etcd/auth/__init__.py
etcd3wrapper/_autogen/etcd/auth/authpb/__init__.py
etcd3wrapper/_autogen/etcd/auth/authpb/auth_pb2.py
etcd3wrapper/_autogen/etcd/auth/authpb/auth_pb2_grpc.py
etcd3wrapper/_autogen/etcd/etcdserver/__init__.py
etcd3wrapper/_autogen/etcd/etcdserver/etcdserverpb/__init__.py
etcd3wrapper/_autogen/etcd/etcdserver/etcdserverpb/rpc_pb2.py
etcd3wrapper/_autogen/etcd/etcdserver/etcdserverpb/rpc_pb2_grpc.py
etcd3wrapper/_autogen/etcd/mvcc/__init__.py
etcd3wrapper/_autogen/etcd/mvcc/mvccpb/__init__.py
etcd3wrapper/_autogen/etcd/mvcc/mvccpb/kv_pb2.py
etcd3wrapper/_autogen/etcd/mvcc/mvccpb/kv_pb2_grpc.py
etcd3wrapper/_autogen/gogoproto/__init__.py
etcd3wrapper/_autogen/gogoproto/gogo_pb2.py
etcd3wrapper/_autogen/gogoproto/gogo_pb2_grpc.py
etcd3wrapper/_autogen/google/__init__.py
etcd3wrapper/_autogen/google/api/__init__.py
etcd3wrapper/_autogen/google/api/annotations_pb2.py
etcd3wrapper/_autogen/google/api/annotations_pb2_grpc.py
etcd3wrapper/_autogen/google/api/http_pb2.py
etcd3wrapper/_autogen/google/api/http_pb2_grpc.py
etcd3wrapper-0.0.1.dist-info/METADATA
etcd3wrapper-0.0.1.dist-info/RECORD
etcd3wrapper-0.0.1.dist-info/WHEEL
etcd3wrapper-0.0.1.dist-info/top_level.txt
