Metadata-Version: 2.1
Name: etcd3wrapper
Version: 0.0.1
Summary: Python 3 etcd3 wrapper for protobuf
Home-page: UNKNOWN
Author: Andrey Cizov
Author-email: acizov@gmail.com
License: UNKNOWN
Platform: UNKNOWN
Requires-Dist: protobuf-gen (>=0.0.2)
